gddkia_impediments_on_roads-0.1.1.dist-info/DESCRIPTION.rst
gddkia_impediments_on_roads-0.1.1.dist-info/METADATA
gddkia_impediments_on_roads-0.1.1.dist-info/RECORD
gddkia_impediments_on_roads-0.1.1.dist-info/WHEEL
gddkia_impediments_on_roads-0.1.1.dist-info/metadata.json
gddkia_impediments_on_roads-0.1.1.dist-info/top_level.txt
impediments/__init__.py
impediments/constants.py
impediments/utils.py
